mltable/__init__.py
mltable/_utils.py
mltable/_validation_and_error_handler.py
mltable/mltable.py
mltable/_aml_utilities/__init__.py
mltable/_aml_utilities/_aml_rest_client_helper.py
mltable/_aml_utilities/_azureml_token_authentication.py
mltable/_aml_utilities/_restclient/__init__.py
mltable/_aml_utilities/_restclient/_azure_machine_learning_workspaces.py
mltable/_aml_utilities/_restclient/_configuration.py
mltable/_aml_utilities/_restclient/_patch.py
mltable/_aml_utilities/_restclient/_version.py
mltable/_aml_utilities/_restclient/models.py
mltable/_aml_utilities/_restclient/dataset/__init__.py
mltable/_aml_utilities/_restclient/dataset/_azure_machine_learning_workspaces.py
mltable/_aml_utilities/_restclient/dataset/_configuration.py
mltable/_aml_utilities/_restclient/dataset/_patch.py
mltable/_aml_utilities/_restclient/dataset/_vendor.py
mltable/_aml_utilities/_restclient/dataset/_version.py
mltable/_aml_utilities/_restclient/dataset/py.typed
mltable/_aml_utilities/_restclient/dataset/models/__init__.py
mltable/_aml_utilities/_restclient/dataset/models/_azure_machine_learning_workspaces_enums.py
mltable/_aml_utilities/_restclient/dataset/models/_models.py
mltable/_aml_utilities/_restclient/dataset/models/_models_py3.py
mltable/_aml_utilities/_restclient/dataset/operations/__init__.py
mltable/_aml_utilities/_restclient/dataset/operations/_data_version_operations.py
mltable/_aml_utilities/_restclient/token/__init__.py
mltable/_aml_utilities/_restclient/token/_azure_machine_learning_workspaces.py
mltable/_aml_utilities/_restclient/token/_configuration.py
mltable/_aml_utilities/_restclient/token/_patch.py
mltable/_aml_utilities/_restclient/token/_vendor.py
mltable/_aml_utilities/_restclient/token/_version.py
mltable/_aml_utilities/_restclient/token/py.typed
mltable/_aml_utilities/_restclient/token/aio/__init__.py
mltable/_aml_utilities/_restclient/token/aio/_azure_machine_learning_workspaces.py
mltable/_aml_utilities/_restclient/token/aio/_configuration.py
mltable-1.6.3.dist-info/licenses/LICENSE.txt
mltable-1.6.3.dist-info/METADATA
mltable-1.6.3.dist-info/WHEEL
mltable-1.6.3.dist-info/top_level.txt
mltable-1.6.3.dist-info/RECORD
