Metadata-Version: 2.4
Name: mltable
Version: 1.6.3
Summary: Contains MLTable loading and authoring apis for the mltable package.
Home-page: https://docs.microsoft.com/python/api/overview/azure/ml/?view=azure-ml-py
Author: Microsoft Corp
License: Proprietary https://aka.ms/azureml-preview-sdk-license 
Classifier: Development Status :: 5 - Production/Stable
Classifier: Intended Audience :: Developers
Classifier: Intended Audience :: Science/Research
Classifier: License :: Other/Proprietary License
Classifier: Programming Language :: Python
Classifier: Programming Language :: Python :: 3 :: Only
Classifier: Programming Language :: Python :: 3.6
Classifier: Programming Language :: Python :: 3.7
Classifier: Programming Language :: Python :: 3.8
Classifier: Programming Language :: Python :: 3.9
Classifier: Programming Language :: Python :: 3.10
Classifier: Programming Language :: Python :: 3.11
Classifier: Programming Language :: Python :: 3.12
Classifier: Operating System :: MacOS
Classifier: Operating System :: Microsoft :: Windows
Classifier: Operating System :: POSIX :: Linux
Classifier: Topic :: Scientific/Engineering
Requires-Python: >=3.6,< 4.0
License-File: LICENSE.txt
Requires-Dist: azureml-dataprep[parquet]<5.5.0a,>=5.1.0a
Requires-Dist: pyyaml<7.0.0,>=5.1.0
Requires-Dist: jsonschema<5.0.0,>=4.0.0
Requires-Dist: msrest>=0.6.18
Requires-Dist: azure-core!=1.22.0,<2.0.0,>=1.8.0
Requires-Dist: azure-mgmt-core<2.0.0,>=1.3.0
Requires-Dist: python-dateutil<3.0.0,>=2.7.3
Requires-Dist: cryptography!=1.9,!=2.0.*,!=2.1.*,!=2.2.*
Requires-Dist: PyJWT<3.0.0
Requires-Dist: pytz
Provides-Extra: azure-ai-ml
Requires-Dist: azure-ai-ml; extra == "azure-ai-ml"
Dynamic: author
Dynamic: classifier
Dynamic: description
Dynamic: description-content-type
Dynamic: home-page
Dynamic: license
Dynamic: license-file
Dynamic: provides-extra
Dynamic: requires-dist
Dynamic: requires-python
Dynamic: summary
